src/alpha_vantage_mcp/__init__.py
src/alpha_vantage_mcp/server.py
src/alpha_vantage_mcp/tools.py
orange_alpha_vantage_mcp-0.1.0.dist-info/METADATA
orange_alpha_vantage_mcp-0.1.0.dist-info/WHEEL
orange_alpha_vantage_mcp-0.1.0.dist-info/entry_points.txt
orange_alpha_vantage_mcp-0.1.0.dist-info/licenses/LICENSE
orange_alpha_vantage_mcp-0.1.0.dist-info/RECORD
