Metadata-Version: 2.4
Name: orange-alpha-vantage-mcp
Version: 0.1.0
Summary: Add your description here
Author-email: berlinbra <BMBpsn@gmail.com>
License-File: LICENSE
Requires-Python: >=3.12
Requires-Dist: httpx>=0.28.1
Requires-Dist: mcp>=1.1.2
